pear_pipecat-0.1.2.dist-info/licenses/LICENSE
pipecat/__init__.py
pipecat/adapters/__init__.py
pipecat/adapters/base_llm_adapter.py
pipecat/adapters/schemas/__init__.py
pipecat/adapters/schemas/function_schema.py
pipecat/adapters/schemas/tools_schema.py
pipecat/adapters/services/__init__.py
pipecat/adapters/services/anthropic_adapter.py
pipecat/adapters/services/gemini_adapter.py
pipecat/adapters/services/open_ai_adapter.py
pipecat/adapters/services/open_ai_realtime_adapter.py
pipecat/audio/__init__.py
pipecat/audio/utils.py
pipecat/audio/filters/__init__.py
pipecat/audio/filters/base_audio_filter.py
pipecat/audio/filters/koala_filter.py
pipecat/audio/filters/krisp_filter.py
pipecat/audio/filters/noisereduce_filter.py
pipecat/audio/mixers/__init__.py
pipecat/audio/mixers/base_audio_mixer.py
pipecat/audio/mixers/soundfile_mixer.py
pipecat/audio/resamplers/__init__.py
pipecat/audio/resamplers/base_audio_resampler.py
pipecat/audio/resamplers/resampy_resampler.py
pipecat/audio/resamplers/soxr_resampler.py
pipecat/audio/vad/__init__.py
pipecat/audio/vad/silero.py
pipecat/audio/vad/vad_analyzer.py
pipecat/audio/vad/data/__init__.py
pipecat/audio/vad/data/silero_vad.onnx
pipecat/clocks/__init__.py
pipecat/clocks/base_clock.py
pipecat/clocks/system_clock.py
pipecat/frames/__init__.py
pipecat/frames/frames.proto
pipecat/frames/frames.py
pipecat/frames/protobufs/frames_pb2.py
pipecat/metrics/__init__.py
pipecat/metrics/metrics.py
pipecat/observers/__init__.py
pipecat/observers/base_observer.py
pipecat/observers/loggers/__init__.py
pipecat/observers/loggers/llm_log_observer.py
pipecat/observers/loggers/transcription_log_observer.py
pipecat/pipeline/__init__.py
pipecat/pipeline/base_pipeline.py
pipecat/pipeline/base_task.py
pipecat/pipeline/parallel_pipeline.py
pipecat/pipeline/pipeline.py
pipecat/pipeline/runner.py
pipecat/pipeline/sync_parallel_pipeline.py
pipecat/pipeline/task.py
pipecat/pipeline/task_observer.py
pipecat/pipeline/to_be_updated/merge_pipeline.py
pipecat/processors/__init__.py
pear_pipecat-0.1.2.dist-info/METADATA
pear_pipecat-0.1.2.dist-info/WHEEL
pear_pipecat-0.1.2.dist-info/top_level.txt
pear_pipecat-0.1.2.dist-info/RECORD
