Metadata-Version: 2.4
Name: pear-pipecat
Version: 0.1.2
Summary: An open source framework for voice (and multimodal) assistants
License: BSD 2-Clause License
Project-URL: Source, https://github.com/pipecat-ai/pipecat
Project-URL: Website, https://pipecat.ai
Keywords: webrtc,audio,video,ai
Classifier: Development Status :: 5 - Production/Stable
Classifier: Intended Audience :: Developers
Classifier: License :: OSI Approved :: BSD License
Classifier: Topic :: Communications :: Conferencing
Classifier: Topic :: Multimedia :: Sound/Audio
Classifier: Topic :: Multimedia :: Video
Classifier: Topic :: Scientific/Engineering :: Artificial Intelligence
Requires-Python: >=3.10
License-File: LICENSE
Requires-Dist: aiohttp~=3.11.13
Requires-Dist: audioop-lts~=0.2.1; python_version >= "3.13"
Requires-Dist: loguru~=0.7.3
Requires-Dist: Markdown~=3.7
Requires-Dist: numpy~=1.26.4
Requires-Dist: Pillow~=11.1.0
Requires-Dist: protobuf~=5.29.3
Requires-Dist: pydantic~=2.10.6
Requires-Dist: pyloudnorm~=0.1.1
Requires-Dist: resampy~=0.4.3
Requires-Dist: soxr~=0.5.0
Requires-Dist: openai~=1.59.6
Provides-Extra: anthropic
Requires-Dist: anthropic~=0.47.2; extra == "anthropic"
Provides-Extra: assemblyai
Requires-Dist: assemblyai~=0.36.0; extra == "assemblyai"
Provides-Extra: aws
Requires-Dist: boto3~=1.35.99; extra == "aws"
Provides-Extra: azure
Requires-Dist: azure-cognitiveservices-speech~=1.42.0; extra == "azure"
Provides-Extra: canonical
Requires-Dist: aiofiles~=24.1.0; extra == "canonical"
Provides-Extra: cartesia
Requires-Dist: cartesia~=1.3.1; extra == "cartesia"
Requires-Dist: websockets~=13.1; extra == "cartesia"
Provides-Extra: cerebras
Provides-Extra: deepseek
Provides-Extra: daily
Requires-Dist: daily-python~=0.15.0; extra == "daily"
Provides-Extra: deepgram
Requires-Dist: deepgram-sdk~=3.8.0; extra == "deepgram"
Provides-Extra: elevenlabs
Requires-Dist: websockets~=13.1; extra == "elevenlabs"
Provides-Extra: fal
Requires-Dist: fal-client~=0.5.6; extra == "fal"
Provides-Extra: fish
Requires-Dist: ormsgpack~=1.7.0; extra == "fish"
Requires-Dist: websockets~=13.1; extra == "fish"
Provides-Extra: gladia
Requires-Dist: websockets~=13.1; extra == "gladia"
Provides-Extra: google
Requires-Dist: google-cloud-speech~=2.31.0; extra == "google"
Requires-Dist: google-cloud-texttospeech~=2.25.0; extra == "google"
Requires-Dist: google-genai~=1.3.0; extra == "google"
Requires-Dist: google-generativeai~=0.8.4; extra == "google"
Provides-Extra: grok
Provides-Extra: groq
Provides-Extra: gstreamer
Requires-Dist: pygobject~=3.50.0; extra == "gstreamer"
Provides-Extra: fireworks
Provides-Extra: krisp
Requires-Dist: pipecat-ai-krisp~=0.3.0; extra == "krisp"
Provides-Extra: koala
Requires-Dist: pvkoala~=2.0.3; extra == "koala"
Provides-Extra: langchain
Requires-Dist: langchain~=0.3.14; extra == "langchain"
Requires-Dist: langchain-community~=0.3.14; extra == "langchain"
Requires-Dist: langchain-openai~=0.3.0; extra == "langchain"
Provides-Extra: livekit
Requires-Dist: livekit~=0.19.1; extra == "livekit"
Requires-Dist: livekit-api~=0.8.1; extra == "livekit"
Requires-Dist: tenacity~=9.0.0; extra == "livekit"
Provides-Extra: lmnt
Requires-Dist: websockets~=13.1; extra == "lmnt"
Provides-Extra: local
Requires-Dist: pyaudio~=0.2.14; extra == "local"
Provides-Extra: moondream
Requires-Dist: einops~=0.8.0; extra == "moondream"
Requires-Dist: timm~=1.0.13; extra == "moondream"
Requires-Dist: transformers~=4.48.0; extra == "moondream"
Provides-Extra: nim
Provides-Extra: noisereduce
Requires-Dist: noisereduce~=3.0.3; extra == "noisereduce"
Provides-Extra: openai
Requires-Dist: websockets~=13.1; extra == "openai"
Provides-Extra: openpipe
Requires-Dist: openpipe~=4.45.0; extra == "openpipe"
Provides-Extra: perplexity
Provides-Extra: playht
Requires-Dist: pyht~=0.1.12; extra == "playht"
Requires-Dist: websockets~=13.1; extra == "playht"
Provides-Extra: rime
Requires-Dist: websockets~=13.1; extra == "rime"
Provides-Extra: riva
Requires-Dist: nvidia-riva-client~=2.18.0; extra == "riva"
Provides-Extra: sentry
Requires-Dist: sentry-sdk~=2.20.0; extra == "sentry"
Provides-Extra: silero
Requires-Dist: onnxruntime~=1.20.1; extra == "silero"
Provides-Extra: simli
Requires-Dist: simli-ai~=0.1.10; extra == "simli"
Provides-Extra: soundfile
Requires-Dist: soundfile~=0.13.0; extra == "soundfile"
Provides-Extra: together
Provides-Extra: websocket
Requires-Dist: websockets~=13.1; extra == "websocket"
Requires-Dist: fastapi~=0.115.6; extra == "websocket"
Provides-Extra: whisper
Requires-Dist: faster-whisper~=1.1.1; extra == "whisper"
Provides-Extra: openrouter
Dynamic: license-file
